[
  {
    "site_no": "E10096",
    "new_areaname": "高雄市",
    "site_name": "楠梓區後勁段四小段152、156地號處萬應公廟場址(測試用)",
    "site_area": 1213.0,
    "site_kind": "工廠",
    "situation": "公告解除控制場址",
    "situation_date": "2015-07-28T00:00:00",
    "soil_pollution": "總石油碳氫化合物",
    "gw_pollution": "無",
    "is_restrain": "否",
    "chk": "是",
    "situation_class": "Control",
    "coorx": 179736.0,
    "coory": 2512684.0,
    "stage": "4",
    "name": "999-0-01",
    "description": "結束程序",
    "idx": 1,
    "progress": "100%",
    "ismonitorstate": false
  },
  {
    "site_no": "E00015",
    "new_areaname": "高雄市",
    "site_name": "台灣中油股份有限公司苓雅寮儲運所(特貿二南)場址(測試用)",
    "site_area": 15897.0,
    "site_kind": "工廠",
    "situation": "公告解除整治場址",
    "situation_date": "2015-07-24T00:00:00",
    "soil_pollution": "總石油碳氫化合物",
    "gw_pollution": "無",
    "is_restrain": "是",
    "chk": "是",
    "situation_class": "Rem",
    "coorx": 177908.455660875,
    "coory": 2501350.40389957,
    "stage": "4",
    "name": "999-0-01",
    "description": "結束程序",
    "idx": 1,
    "progress": "100%",
    "ismonitorstate": false
  },
  {
    "site_no": "S10066",
    "new_areaname": "高雄市",
    "site_name": "台灣塑膠股份有限公司仁武廠(測試用)",
    "site_area": 353866.0,
    "site_kind": "工廠",
    "situation": "公告為控制場址",
    "situation_date": "2010-02-25T00:00:00",
    "soil_pollution": "1,2-二氯乙烷;順-1,2-二氯乙烯;四氯乙烯;氯乙烯",
    "gw_pollution": "苯;四氯化碳;氯仿;1,2-二氯乙烷;1,1-二氯乙烯;順-1,2-二氯乙烯;四氯乙烯;三氯乙烯;氯乙烯;二氯甲烷;1,1,2-三氯乙烷",
    "is_restrain": "否",
    "chk": "是",
    "situation_class": "Control",
    "coorx": 181715.0,
    "coory": 2511888.0,
    "stage": null,
    "name": null,
    "description": null,
    "idx": null,
    "progress": "0",
    "ismonitorstate": false
  },
  {
    "site_no": "S10043",
    "new_areaname": "高雄市",
    "site_name": "南亞塑膠工業股份有限公司林園廠(測試用)",
    "site_area": 63870.0,
    "site_kind": "工廠",
    "situation": "依細則第八條限期採取適當措施",
    "situation_date": "2008-12-25T00:00:00",
    "soil_pollution": "總石油碳氫化合物",
    "gw_pollution": "無",
    "is_restrain": "否",
    "chk": "是",
    "situation_class": "Limit",
    "coorx": 189407.0,
    "coory": 2486136.0,
    "stage": null,
    "name": null,
    "description": null,
    "idx": null,
    "progress": "0",
    "ismonitorstate": false
  },
  {
    "site_no": "E10084",
    "new_areaname": "高雄市",
    "site_name": "台灣中油股份有限公司煉製事業部高雄煉油廠工廠區後勁段月眉小段756、758-3、801地號土地(測試用)",
    "site_area": 57248.0,
    "site_kind": "工廠",
    "situation": "公告為控制場址",
    "situation_date": "2008-09-15T00:00:00",
    "soil_pollution": "總石油碳氫化合物",
    "gw_pollution": "無",
    "is_restrain": "否",
    "chk": "是",
    "situation_class": "Control",
    "coorx": 179736.54,
    "coory": 2512684.2,
    "stage": null,
    "name": null,
    "description": null,
    "idx": null,
    "progress": "0",
    "ismonitorstate": false
  },
  {
    "site_no": "E10016",
    "new_areaname": "高雄市",
    "site_name": "台灣中油股份有限公司煉製事業部高雄煉油廠工廠區東門區域場址(測試用)",
    "site_area": 327903.0,
    "site_kind": "工廠",
    "situation": "公告為控制場址",
    "situation_date": "2007-11-02T00:00:00",
    "soil_pollution": "苯;二甲苯;乙苯;總石油碳氫化合物",
    "gw_pollution": "無",
    "is_restrain": "否",
    "chk": "是",
    "situation_class": "Control",
    "coorx": 180109.0,
    "coory": 2512690.08,
    "stage": null,
    "name": null,
    "description": null,
    "idx": null,
    "progress": "0",
    "ismonitorstate": false
  },
  {
    "site_no": "E10007",
    "new_areaname": "高雄市",
    "site_name": "台灣中油股份有限公司煉製事業部高雄煉油廠工廠區後勁段月眉小段758-1、758-5、758-6地號土地(測試用)",
    "site_area": 24964.0,
    "site_kind": "工廠",
    "situation": "公告為控制場址",
    "situation_date": "2007-05-17T00:00:00",
    "soil_pollution": "苯;甲苯;二甲苯;總石油碳氫化合物",
    "gw_pollution": "無",
    "is_restrain": "否",
    "chk": "是",
    "situation_class": "Control",
    "coorx": 179400.0,
    "coory": 2512300.0,
    "stage": null,
    "name": null,
    "description": null,
    "idx": null,
    "progress": "0",
    "ismonitorstate": false
  },
  {
    "site_no": "E00020",
    "new_areaname": "高雄市",
    "site_name": "台灣中油股份有限公司煉製事業部高雄煉油廠工廠區4筆地號土地(本市楠梓區後勁段月眉小段736、736-1、737、841地號)之部分綠帶(測試用)",
    "site_area": 84650.0,
    "site_kind": "工廠",
    "situation": "公告為控制場址",
    "situation_date": "2005-10-07T00:00:00",
    "soil_pollution": "苯;總石油碳氫化合物",
    "gw_pollution": "無",
    "is_restrain": "否",
    "chk": "是",
    "situation_class": "Control",
    "coorx": 179532.353861,
    "coory": 2513338.9975,
    "stage": null,
    "name": null,
    "description": null,
    "idx": null,
    "progress": "0",
    "ismonitorstate": false
  },
  {
    "site_no": "E00010",
    "new_areaname": "高雄市",
    "site_name": "台灣中油股份有限公司煉製事業部高雄煉油廠工廠區(不含P-37油槽區)(測試用)",
    "site_area": 1767530.0,
    "site_kind": "工廠",
    "situation": "公告為控制場址",
    "situation_date": "2005-09-13T00:00:00",
    "soil_pollution": "無",
    "gw_pollution": "苯;甲苯;總酚",
    "is_restrain": "否",
    "chk": "是",
    "situation_class": "Control",
    "coorx": 180223.58,
    "coory": 2512361.79,
    "stage": null,
    "name": null,
    "description": null,
    "idx": null,
    "progress": "0",
    "ismonitorstate": false
  },
  {
    "site_no": "E10122",
    "new_areaname": "高雄市",
    "site_name": "CE168(測試用)",
    "site_area": null,
    "site_kind": "軍事場址",
    "situation": "公告為整治場址",
    "situation_date": "2004-03-19T00:00:00",
    "soil_pollution": "鉻;銅;鋅;鎳;總石油碳氫化合物",
    "gw_pollution": "無",
    "is_restrain": "否",
    "chk": "否",
    "situation_class": "Rem",
    "coorx": 0.0,
    "coory": 0.0,
    "stage": "2",
    "name": "A47",
    "description": "是否修正整治計畫再審",
    "idx": 1,
    "progress": "25%",
    "ismonitorstate": false
  },
  {
    "site_no": "S00002",
    "new_areaname": "高雄市",
    "site_name": "高雄縣台灣中油股份有限公司石化事業部林園廠(測試用)",
    "site_area": 980000.0,
    "site_kind": "儲槽",
    "situation": "調查中場址",
    "situation_date": null,
    "soil_pollution": "苯;總石油碳氫化合物",
    "gw_pollution": "苯",
    "is_restrain": "否",
    "chk": "是",
    "situation_class": "Others",
    "coorx": 188763.84,
    "coory": 2488314.73,
    "stage": "1",
    "name": "B1",
    "description": "污染確認",
    "idx": 1,
    "progress": "1%",
    "ismonitorstate": false
  },
  {
    "site_no": "E10123",
    "new_areaname": "高雄市",
    "site_name": "CS089(測試用)",
    "site_area": null,
    "site_kind": "軍事場址",
    "situation": "調查中場址",
    "situation_date": null,
    "soil_pollution": "銅;總石油碳氫化合物",
    "gw_pollution": "無",
    "is_restrain": "否",
    "chk": "否",
    "situation_class": "Others",
    "coorx": 0.0,
    "coory": 0.0,
    "stage": null,
    "name": null,
    "description": null,
    "idx": null,
    "progress": "0",
    "ismonitorstate": false
  },
  {
    "site_no": "E10033",
    "new_areaname": "高雄市",
    "site_name": "中油大林廠(測試用)",
    "site_area": null,
    "site_kind": "工廠",
    "situation": "調查中場址",
    "situation_date": null,
    "soil_pollution": "無",
    "gw_pollution": "TPH-D 總石油碳氫化合物-柴油類有機物(C9-C28)",
    "is_restrain": "否",
    "chk": "否",
    "situation_class": "Others",
    "coorx": 182405.0,
    "coory": 2492540.0,
    "stage": null,
    "name": null,
    "description": null,
    "idx": null,
    "progress": "0",
    "ismonitorstate": false
  },
  {
    "site_no": "F10055",
    "new_areaname": "新北市",
    "site_name": "原台灣金屬業股份有限公司及其所屬三條廢煙道地區(部分)(測試用)",
    "site_area": 297668.0,
    "site_kind": "工廠",
    "situation": "公告為控制場址",
    "situation_date": "2010-03-26T00:00:00",
    "soil_pollution": "砷;鎘;鉻;銅;鉛;鋅;汞;阿特靈;地特靈;二甲苯;氯仿;順-1,2-二氯乙烯;總石油碳氫化合物;戴奧辛;多氯聯苯",
    "gw_pollution": "氨氮;甲苯;TPH-D 總石油碳氫化合物-柴油類有機物(C9-C28);砷;錳;1,2-二氯乙烷;甲基第三丁基醚;毒殺芬",
    "is_restrain": "否",
    "chk": "否",
    "situation_class": "Control",
    "coorx": 337216.0,
    "coory": 2779258.0,
    "stage": null,
    "name": null,
    "description": null,
    "idx": null,
    "progress": "0",
    "ismonitorstate": false
  },
  {
    "site_no": "F00018",
    "new_areaname": "新北市",
    "site_name": "臺北縣新莊市原正泰化工廠污染案(測試用)",
    "site_area": 0.0,
    "site_kind": "工廠",
    "situation": "調查中場址",
    "situation_date": null,
    "soil_pollution": "無",
    "gw_pollution": "無",
    "is_restrain": "否",
    "chk": "否",
    "situation_class": "Others",
    "coorx": 292787.885,
    "coory": 2766873.243,
    "stage": "1",
    "name": "B1",
    "description": "污染確認",
    "idx": 1,
    "progress": "1%",
    "ismonitorstate": false
  },
  {
    "site_no": "K10021",
    "new_areaname": "苗栗縣",
    "site_name": "竹南鎮鹽館前段大厝小段154地號(國泰北側)(測試用)",
    "site_area": 73662.0,
    "site_kind": "其他",
    "situation": "公告地下水受污染限制使用地區及限制事項",
    "situation_date": "2009-08-31T00:00:00",
    "soil_pollution": "無",
    "gw_pollution": "氯乙烯",
    "is_restrain": "否",
    "chk": "否",
    "situation_class": "GW",
    "coorx": 237634.64511808514,
    "coory": 2730010.9350150959,
    "stage": null,
    "name": null,
    "description": null,
    "idx": null,
    "progress": "0",
    "ismonitorstate": false
  },
  {
    "site_no": "K00006",
    "new_areaname": "苗栗縣",
    "site_name": "台灣氯乙烯工業股份有限公司頭份廠(測試用)",
    "site_area": 50000.0,
    "site_kind": "工廠",
    "situation": "公告為整治場址",
    "situation_date": "2006-03-27T00:00:00",
    "soil_pollution": "無",
    "gw_pollution": "苯;1,2-二氯乙烷;三氯乙烯;氯乙烯",
    "is_restrain": "否",
    "chk": "是",
    "situation_class": "Rem",
    "coorx": 238732.0,
    "coory": 2730151.0,
    "stage": null,
    "name": null,
    "description": null,
    "idx": null,
    "progress": "0",
    "ismonitorstate": false
  },
  {
    "site_no": "B00020",
    "new_areaname": "雲林縣",
    "site_name": "台中市北屯區景美段380地號(測試用)",
    "site_area": 13934.0,
    "site_kind": "其他",
    "situation": "公告為控制場址",
    "situation_date": "2021-03-04T00:00:00",
    "soil_pollution": "無",
    "gw_pollution": "無",
    "is_restrain": "否",
    "chk": "否",
    "situation_class": "Control",
    "coorx": 220171.0,
    "coory": 2674075.0,
    "stage": "1",
    "name": "B3",
    "description": "公告為控制場址",
    "idx": 1,
    "progress": "10%",
    "ismonitorstate": false
  },
  {
    "site_no": "B10009",
    "new_areaname": "嘉義縣",
    "site_name": "東海大學附設國小(測試用)",
    "site_area": 0.0,
    "site_kind": "其他",
    "situation": "公告為控制場址",
    "situation_date": "2021-03-04T00:00:00",
    "soil_pollution": "銅;可氯丹;氯仿;戴奧辛",
    "gw_pollution": "無",
    "is_restrain": "否",
    "chk": "否",
    "situation_class": "Control",
    "coorx": 210084.0,
    "coory": 2675092.0,
    "stage": "1",
    "name": "B3",
    "description": "公告為控制場址",
    "idx": 1,
    "progress": "10%",
    "ismonitorstate": false
  },
  {
    "site_no": "B10010",
    "new_areaname": "臺中市",
    "site_name": "中清路202號旁(測試用)",
    "site_area": 0.0,
    "site_kind": "其他",
    "situation": "公告為控制場址",
    "situation_date": "2021-03-04T00:00:00",
    "soil_pollution": "無",
    "gw_pollution": "無",
    "is_restrain": "否",
    "chk": "否",
    "situation_class": "Control",
    "coorx": 214779.0,
    "coory": 2677748.0,
    "stage": "1",
    "name": "B3",
    "description": "公告為控制場址",
    "idx": 1,
    "progress": "10%",
    "ismonitorstate": false
  },
  {
    "site_no": "B10025",
    "new_areaname": "臺中市",
    "site_name": "慧國工業股份有限公司(測試用)",
    "site_area": 60.0,
    "site_kind": "工廠",
    "situation": "公告為控制場址",
    "situation_date": "2021-03-04T00:00:00",
    "soil_pollution": "總石油碳氫化合物",
    "gw_pollution": "無",
    "is_restrain": "否",
    "chk": "是",
    "situation_class": "Control",
    "coorx": 210356.03932941926,
    "coory": 2673651.20253211,
    "stage": "4",
    "name": "A87",
    "description": "改善計畫契約是否到期",
    "idx": 3,
    "progress": "40%",
    "ismonitorstate": false
  },
  {
    "site_no": "J10013",
    "new_areaname": "新竹縣",
    "site_name": "新竹科學工業園區寶山地區附近地下水污染案(新竹縣) (測試用)",
    "site_area": 4307.96,
    "site_kind": "其他",
    "situation": "公告地下水受污染限制使用地區及限制事項",
    "situation_date": "2009-10-19T00:00:00",
    "soil_pollution": "無",
    "gw_pollution": "總硬度;氨氮;甲苯;TPH-D 總石油碳氫化合物-柴油類有機物(C9-C28);鐵;氯苯;三氯乙烯;可氯丹",
    "is_restrain": "否",
    "chk": "是",
    "situation_class": "GW",
    "coorx": 251204.92614933394,
    "coory": 2740578.9593403428,
    "stage": null,
    "name": null,
    "description": null,
    "idx": null,
    "progress": "0",
    "ismonitorstate": false
  },
  {
    "site_no": "H00001",
    "new_areaname": "桃園市",
    "site_name": "臺灣美國無線電公司RCA原桃園廠(測試用)",
    "site_area": 80818.0,
    "site_kind": "工廠",
    "situation": "公告為整治場址",
    "situation_date": "2004-03-19T00:00:00",
    "soil_pollution": "無",
    "gw_pollution": "1,1-二氯乙烯;四氯乙烯;三氯乙烯;氯乙烯",
    "is_restrain": "否",
    "chk": "是",
    "situation_class": "Rem",
    "coorx": 278085.27,
    "coory": 2764256.21,
    "stage": null,
    "name": null,
    "description": null,
    "idx": null,
    "progress": "0",
    "ismonitorstate": false
  },
  {
    "site_no": "H10100",
    "new_areaname": "桃園市",
    "site_name": "瑞昇金屬工業股份有限公司桃園廠(測試用)",
    "site_area": 3099.0,
    "site_kind": "工廠",
    "situation": "調查中場址",
    "situation_date": null,
    "soil_pollution": "無",
    "gw_pollution": "三氯乙烯",
    "is_restrain": "否",
    "chk": "否",
    "situation_class": "Others",
    "coorx": 274608.0,
    "coory": 2764857.0,
    "stage": null,
    "name": null,
    "description": null,
    "idx": null,
    "progress": "0",
    "ismonitorstate": false
  },
  {
    "site_no": "D00001",
    "new_areaname": "臺南市",
    "site_name": "中國石油化學工業開發股份有限公司安順廠台南市中石化安順廠污染案(測試用)",
    "site_area": 181600.0,
    "site_kind": "其他",
    "situation": "公告為整治場址",
    "situation_date": "2004-03-19T00:00:00",
    "soil_pollution": "汞;戴奧辛",
    "gw_pollution": "無",
    "is_restrain": "否",
    "chk": "是",
    "situation_class": "Rem",
    "coorx": 160057.987,
    "coory": 2547942.969,
    "stage": null,
    "name": null,
    "description": null,
    "idx": null,
    "progress": "0",
    "ismonitorstate": false
  },
  {
    "site_no": "T00004",
    "new_areaname": "屏東縣",
    "site_name": "屏東縣新園鄉新洋段325、416、419、428、429、430、431、432-6(部分)地號(測試用)",
    "site_area": 47720.0,
    "site_kind": "非法棄置場址",
    "situation": "公告為整治場址",
    "situation_date": "2006-12-05T00:00:00",
    "soil_pollution": "砷;鉻;銅;鉛;鋅;汞;鎳",
    "gw_pollution": "無",
    "is_restrain": "否",
    "chk": "是",
    "situation_class": "Rem",
    "coorx": 194406.0,
    "coory": 2495432.0,
    "stage": null,
    "name": null,
    "description": null,
    "idx": null,
    "progress": "0",
    "ismonitorstate": false
  },
  {
    "site_no": "V00047",
    "new_areaname": "臺東縣",
    "site_name": "1010320(測試用)",
    "site_area": 20000.0,
    "site_kind": "農地",
    "situation": "公告為整治場址",
    "situation_date": "2004-03-19T00:00:00",
    "soil_pollution": "銅",
    "gw_pollution": "無",
    "is_restrain": "否",
    "chk": "否",
    "situation_class": "Rem",
    "coorx": 268151.03456347657,
    "coory": 2517902.1751921503,
    "stage": "2",
    "name": "123-2-39",
    "description": "調查及評估計畫之調查結果提至EPA評定處理等級",
    "idx": 1,
    "progress": "16%",
    "ismonitorstate": false
  },
  {
    "site_no": "X00014",
    "new_areaname": "澎湖縣",
    "site_name": "台灣中油湖西供油中心(測試用)",
    "site_area": null,
    "site_kind": "儲槽",
    "situation": "調查中場址",
    "situation_date": null,
    "soil_pollution": "無",
    "gw_pollution": "無",
    "is_restrain": "否",
    "chk": "否",
    "situation_class": "Others",
    "coorx": 112776.15705786555,
    "coory": 2608703.3261119849,
    "stage": null,
    "name": null,
    "description": null,
    "idx": null,
    "progress": "0",
    "ismonitorstate": false
  },
  {
    "site_no": "E00015",
    "new_areaname": "台北市",
    "site_name": "台灣中油股份有限公司苓雅寮儲運所(特貿二南)場址(測試用)",
    "site_area": 15897.0,
    "site_kind": "工廠",
    "situation": "公告解除整治場址",
    "situation_date": "2015-07-24T00:00:00",
    "soil_pollution": "總石油碳氫化合物",
    "gw_pollution": "無",
    "is_restrain": "是",
    "chk": "是",
    "situation_class": "Rem",
    "coorx": 177908.455660875,
    "coory": 2501350.40389957,
    "stage": "4",
    "name": "999-0-01",
    "description": "結束程序",
    "idx": 1,
    "progress": "100%",
    "ismonitorstate": false
  },
  {
    "site_no": "E00015",
    "new_areaname": "南投縣",
    "site_name": "台灣中油股份有限公司苓雅寮儲運所(特貿二南)場址(測試用)",
    "site_area": 15897.0,
    "site_kind": "工廠",
    "situation": "公告解除整治場址",
    "situation_date": "2015-07-24T00:00:00",
    "soil_pollution": "總石油碳氫化合物",
    "gw_pollution": "無",
    "is_restrain": "是",
    "chk": "是",
    "situation_class": "Rem",
    "coorx": 177908.455660875,
    "coory": 2501350.40389957,
    "stage": "4",
    "name": "999-0-01",
    "description": "結束程序",
    "idx": 1,
    "progress": "100%",
    "ismonitorstate": false
  },
  {
    "site_no": "E00015",
    "new_areaname": "彰化縣",
    "site_name": "台灣中油股份有限公司苓雅寮儲運所(特貿二南)場址(測試用)",
    "site_area": 15897.0,
    "site_kind": "工廠",
    "situation": "公告解除整治場址",
    "situation_date": "2015-07-24T00:00:00",
    "soil_pollution": "總石油碳氫化合物",
    "gw_pollution": "無",
    "is_restrain": "是",
    "chk": "是",
    "situation_class": "Rem",
    "coorx": 177908.455660875,
    "coory": 2501350.40389957,
    "stage": "4",
    "name": "999-0-01",
    "description": "結束程序",
    "idx": 1,
    "progress": "100%",
    "ismonitorstate": false
  },
  {
    "site_no": "E00015",
    "new_areaname": "花蓮縣",
    "site_name": "台灣中油股份有限公司苓雅寮儲運所(特貿二南)場址(測試用)",
    "site_area": 15897.0,
    "site_kind": "工廠",
    "situation": "公告解除整治場址",
    "situation_date": "2015-07-24T00:00:00",
    "soil_pollution": "總石油碳氫化合物",
    "gw_pollution": "無",
    "is_restrain": "是",
    "chk": "是",
    "situation_class": "Rem",
    "coorx": 177908.455660875,
    "coory": 2501350.40389957,
    "stage": "4",
    "name": "999-0-01",
    "description": "結束程序",
    "idx": 1,
    "progress": "100%",
    "ismonitorstate": false
  },
  {
    "site_no": "E00015",
    "new_areaname": "嘉義市",
    "site_name": "台灣中油股份有限公司苓雅寮儲運所(特貿二南)場址(測試用)",
    "site_area": 15897.0,
    "site_kind": "工廠",
    "situation": "公告解除整治場址",
    "situation_date": "2015-07-24T00:00:00",
    "soil_pollution": "總石油碳氫化合物",
    "gw_pollution": "無",
    "is_restrain": "是",
    "chk": "是",
    "situation_class": "Rem",
    "coorx": 177908.455660875,
    "coory": 2501350.40389957,
    "stage": "4",
    "name": "999-0-01",
    "description": "結束程序",
    "idx": 1,
    "progress": "100%",
    "ismonitorstate": false
  },
  {
    "site_no": "E00015",
    "new_areaname": "嘉義市",
    "site_name": "台灣中油股份有限公司苓雅寮儲運所(特貿二南)場址(測試用)",
    "site_area": 15897.0,
    "site_kind": "工廠",
    "situation": "公告解除整治場址",
    "situation_date": "2015-07-24T00:00:00",
    "soil_pollution": "總石油碳氫化合物",
    "gw_pollution": "無",
    "is_restrain": "是",
    "chk": "是",
    "situation_class": "Rem",
    "coorx": 177908.455660875,
    "coory": 2501350.40389957,
    "stage": "4",
    "name": "999-0-01",
    "description": "結束程序",
    "idx": 1,
    "progress": "100%",
    "ismonitorstate": false
  },
  {
    "site_no": "E00015",
    "new_areaname": "嘉義市",
    "site_name": "台灣中油股份有限公司苓雅寮儲運所(特貿二南)場址(測試用)",
    "site_area": 15897.0,
    "site_kind": "工廠",
    "situation": "公告解除整治場址",
    "situation_date": "2015-07-24T00:00:00",
    "soil_pollution": "總石油碳氫化合物",
    "gw_pollution": "無",
    "is_restrain": "是",
    "chk": "是",
    "situation_class": "Rem",
    "coorx": 177908.455660875,
    "coory": 2501350.40389957,
    "stage": "4",
    "name": "999-0-01",
    "description": "結束程序",
    "idx": 1,
    "progress": "100%",
    "ismonitorstate": false
  },
  {
    "site_no": "E00015",
    "new_areaname": "金門縣",
    "site_name": "台灣中油股份有限公司苓雅寮儲運所(特貿二南)場址(測試用)",
    "site_area": 15897.0,
    "site_kind": "工廠",
    "situation": "公告解除整治場址",
    "situation_date": "2015-07-24T00:00:00",
    "soil_pollution": "總石油碳氫化合物",
    "gw_pollution": "無",
    "is_restrain": "是",
    "chk": "是",
    "situation_class": "Rem",
    "coorx": 177908.455660875,
    "coory": 2501350.40389957,
    "stage": "4",
    "name": "999-0-01",
    "description": "結束程序",
    "idx": 1,
    "progress": "100%",
    "ismonitorstate": false
  },
  {
    "site_no": "E00015",
    "new_areaname": "金門縣",
    "site_name": "台灣中油股份有限公司苓雅寮儲運所(特貿二南)場址(測試用)",
    "site_area": 15897.0,
    "site_kind": "工廠",
    "situation": "公告解除整治場址",
    "situation_date": "2015-07-24T00:00:00",
    "soil_pollution": "總石油碳氫化合物",
    "gw_pollution": "無",
    "is_restrain": "是",
    "chk": "是",
    "situation_class": "Rem",
    "coorx": 177908.455660875,
    "coory": 2501350.40389957,
    "stage": "4",
    "name": "999-0-01",
    "description": "結束程序",
    "idx": 1,
    "progress": "100%",
    "ismonitorstate": false
  },
  {
    "site_no": "E00015",
    "new_areaname": "連江縣",
    "site_name": "台灣中油股份有限公司苓雅寮儲運所(特貿二南)場址(測試用)",
    "site_area": 15897.0,
    "site_kind": "工廠",
    "situation": "公告解除整治場址",
    "situation_date": "2015-07-24T00:00:00",
    "soil_pollution": "總石油碳氫化合物",
    "gw_pollution": "無",
    "is_restrain": "是",
    "chk": "是",
    "situation_class": "Rem",
    "coorx": 177908.455660875,
    "coory": 2501350.40389957,
    "stage": "4",
    "name": "999-0-01",
    "description": "結束程序",
    "idx": 1,
    "progress": "100%",
    "ismonitorstate": false
  },
  {
    "site_no": "E00015",
    "new_areaname": "連江縣",
    "site_name": "台灣中油股份有限公司苓雅寮儲運所(特貿二南)場址(測試用)",
    "site_area": 15897.0,
    "site_kind": "工廠",
    "situation": "公告解除整治場址",
    "situation_date": "2015-07-24T00:00:00",
    "soil_pollution": "總石油碳氫化合物",
    "gw_pollution": "無",
    "is_restrain": "是",
    "chk": "是",
    "situation_class": "Rem",
    "coorx": 177908.455660875,
    "coory": 2501350.40389957,
    "stage": "4",
    "name": "999-0-01",
    "description": "結束程序",
    "idx": 1,
    "progress": "100%",
    "ismonitorstate": false
  },
  {
    "site_no": "E00015",
    "new_areaname": "連江縣",
    "site_name": "台灣中油股份有限公司苓雅寮儲運所(特貿二南)場址(測試用)",
    "site_area": 15897.0,
    "site_kind": "工廠",
    "situation": "公告解除整治場址",
    "situation_date": "2015-07-24T00:00:00",
    "soil_pollution": "總石油碳氫化合物",
    "gw_pollution": "無",
    "is_restrain": "是",
    "chk": "是",
    "situation_class": "Rem",
    "coorx": 177908.455660875,
    "coory": 2501350.40389957,
    "stage": "4",
    "name": "999-0-01",
    "description": "結束程序",
    "idx": 1,
    "progress": "100%",
    "ismonitorstate": false
  },
  {
    "site_no": "E00015",
    "new_areaname": "台東縣",
    "site_name": "台灣中油股份有限公司苓雅寮儲運所(特貿二南)場址(測試用)",
    "site_area": 15897.0,
    "site_kind": "工廠",
    "situation": "公告解除整治場址",
    "situation_date": "2015-07-24T00:00:00",
    "soil_pollution": "總石油碳氫化合物",
    "gw_pollution": "無",
    "is_restrain": "是",
    "chk": "是",
    "situation_class": "Rem",
    "coorx": 177908.455660875,
    "coory": 2501350.40389957,
    "stage": "4",
    "name": "999-0-01",
    "description": "結束程序",
    "idx": 1,
    "progress": "100%",
    "ismonitorstate": false
  },
  {
    "site_no": "E00015",
    "new_areaname": "台東縣",
    "site_name": "台灣中油股份有限公司苓雅寮儲運所(特貿二南)場址(測試用)",
    "site_area": 15897.0,
    "site_kind": "工廠",
    "situation": "公告解除整治場址",
    "situation_date": "2015-07-24T00:00:00",
    "soil_pollution": "總石油碳氫化合物",
    "gw_pollution": "無",
    "is_restrain": "是",
    "chk": "是",
    "situation_class": "Rem",
    "coorx": 177908.455660875,
    "coory": 2501350.40389957,
    "stage": "4",
    "name": "999-0-01",
    "description": "結束程序",
    "idx": 1,
    "progress": "100%",
    "ismonitorstate": false
  },
  {
    "site_no": "E00015",
    "new_areaname": "台東縣",
    "site_name": "台灣中油股份有限公司苓雅寮儲運所(特貿二南)場址(測試用)",
    "site_area": 15897.0,
    "site_kind": "工廠",
    "situation": "公告解除整治場址",
    "situation_date": "2015-07-24T00:00:00",
    "soil_pollution": "總石油碳氫化合物",
    "gw_pollution": "無",
    "is_restrain": "是",
    "chk": "是",
    "situation_class": "Rem",
    "coorx": 177908.455660875,
    "coory": 2501350.40389957,
    "stage": "4",
    "name": "999-0-01",
    "description": "結束程序",
    "idx": 1,
    "progress": "100%",
    "ismonitorstate": false
  },
  {
    "site_no": "E00015",
    "new_areaname": "宜蘭縣",
    "site_name": "台灣中油股份有限公司苓雅寮儲運所(特貿二南)場址(測試用)",
    "site_area": 15897.0,
    "site_kind": "工廠",
    "situation": "公告解除整治場址",
    "situation_date": "2015-07-24T00:00:00",
    "soil_pollution": "總石油碳氫化合物",
    "gw_pollution": "無",
    "is_restrain": "是",
    "chk": "是",
    "situation_class": "Rem",
    "coorx": 177908.455660875,
    "coory": 2501350.40389957,
    "stage": "4",
    "name": "999-0-01",
    "description": "結束程序",
    "idx": 1,
    "progress": "100%",
    "ismonitorstate": false
  },
  {
    "site_no": "E00015",
    "new_areaname": "新竹市",
    "site_name": "台灣中油股份有限公司苓雅寮儲運所(特貿二南)場址(測試用)",
    "site_area": 15897.0,
    "site_kind": "工廠",
    "situation": "公告解除整治場址",
    "situation_date": "2015-07-24T00:00:00",
    "soil_pollution": "總石油碳氫化合物",
    "gw_pollution": "無",
    "is_restrain": "是",
    "chk": "是",
    "situation_class": "Rem",
    "coorx": 177908.455660875,
    "coory": 2501350.40389957,
    "stage": "4",
    "name": "999-0-01",
    "description": "結束程序",
    "idx": 1,
    "progress": "100%",
    "ismonitorstate": false
  }
]
